.project-version
LICENSE
MANIFEST.in
README.md
pyproject.toml
setup.cfg
setup.py
diagrams_as_code/__init__.py
diagrams_as_code/entrypoint.py
diagrams_as_code/enums.py
diagrams_as_code/resources.py
diagrams_as_code/schema.py
diagrams_as_code.egg-info/PKG-INFO
diagrams_as_code.egg-info/SOURCES.txt
diagrams_as_code.egg-info/dependency_links.txt
diagrams_as_code.egg-info/entry_points.txt
diagrams_as_code.egg-info/requires.txt
diagrams_as_code.egg-info/top_level.txt
requirements/project.txt