Metadata-Version: 2.1
Name: diagrams-as-code
Version: 0.0.4
Summary: Diagrams as code: declarative configurations using YAML for drawing cloud system architectures.
Home-page: https://github.com/dmytrostriletskyi/diagrams-as-code
Author: Dmytro Striletskyi
Author-email: dmytro.striletskyi@gmail.com
License: MIT
Project-URL: Issue Tracker, https://github.com/dmytrostriletskyi/diagrams-as-code/issues
Project-URL: Source Code, https://github.com/dmytrostriletskyi/diagrams-as-code
Project-URL: Download, https://github.com/dmytrostriletskyi/diagrams-as-code/tags
Platform: UNKNOWN
Classifier: Operating System :: OS Independent
Classifier: Intended Audience :: Developers
Classifier: License :: OSI Approved :: MIT License
Classifier: Programming Language :: Python :: 3.10
Classifier: Programming Language :: Python :: 3.11
License-File: LICENSE
